{
  "openapi": "3.0.1",
  "info": {
    "title": "AhorcadoBackend",
    "version": "1.0"
  },
  "paths": {
    "/api/juego/iniciar": {
      "post": {
        "tags": [
          "Juego"
        ],
        "requestBody": {
          "content": {
            "application/json": {
              "schema": {
                "$ref": "#/components/schemas/PalabraEntrada"
              }
            },
            "text/json": {
              "schema": {
                "$ref": "#/components/schemas/PalabraEntrada"
              }
            },
            "application/*+json": {
              "schema": {
                "$ref": "#/components/schemas/PalabraEntrada"
              }
            }
          }
        },
        "responses": {
          "200": {
            "description": "OK"
          }
        }
      }
    },
    "/api/juego/verificar-letra": {
      "post": {
        "tags": [
          "Juego"
        ],
        "requestBody": {
          "content": {
            "application/json": {
              "schema": {
                "$ref": "#/components/schemas/LetraOnlineEntrada"
              }
            },
            "text/json": {
              "schema": {
                "$ref": "#/components/schemas/LetraOnlineEntrada"
              }
            },
            "application/*+json": {
              "schema": {
                "$ref": "#/components/schemas/LetraOnlineEntrada"
              }
            }
          }
        },
        "responses": {
          "200": {
            "description": "OK"
          }
        }
      }
    },
    "/api/juego/reiniciar": {
      "post": {
        "tags": [
          "Juego"
        ],
        "requestBody": {
          "content": {
            "application/json": {
              "schema": {
                "$ref": "#/components/schemas/ReiniciarJuegoEntrada"
              }
            },
            "text/json": {
              "schema": {
                "$ref": "#/components/schemas/ReiniciarJuegoEntrada"
              }
            },
            "application/*+json": {
              "schema": {
                "$ref": "#/components/schemas/ReiniciarJuegoEntrada"
              }
            }
          }
        },
        "responses": {
          "200": {
            "description": "OK"
          }
        }
      }
    },
    "/api/juego/crear-online": {
      "post": {
        "tags": [
          "Juego"
        ],
        "responses": {
          "200": {
            "description": "OK"
          }
        }
      }
    },
    "/api/juego/unirse-online": {
      "post": {
        "tags": [
          "Juego"
        ],
        "requestBody": {
          "content": {
            "application/json": {
              "schema": {
                "$ref": "#/components/schemas/UnirsePartidaEntrada"
              }
            },
            "text/json": {
              "schema": {
                "$ref": "#/components/schemas/UnirsePartidaEntrada"
              }
            },
            "application/*+json": {
              "schema": {
                "$ref": "#/components/schemas/UnirsePartidaEntrada"
              }
            }
          }
        },
        "responses": {
          "200": {
            "description": "OK"
          }
        }
      }
    }
  },
  "components": {
    "schemas": {
      "LetraOnlineEntrada": {
        "type": "object",
        "properties": {
          "letra": {
            "type": "string",
            "nullable": true
          },
          "gameId": {
            "type": "string",
            "nullable": true
          }
        },
        "additionalProperties": false
      },
      "PalabraEntrada": {
        "type": "object",
        "properties": {
          "palabra": {
            "type": "string",
            "nullable": true
          },
          "modo": {
            "type": "string",
            "nullable": true
          }
        },
        "additionalProperties": false
      },
      "ReiniciarJuegoEntrada": {
        "type": "object",
        "properties": {
          "gameId": {
            "type": "string",
            "nullable": true
          }
        },
        "additionalProperties": false
      },
      "UnirsePartidaEntrada": {
        "type": "object",
        "properties": {
          "gameId": {
            "type": "string",
            "nullable": true
          }
        },
        "additionalProperties": false
      }
    }
  }
}